setup.cfg
setup.py
twyla.logging.egg-info/PKG-INFO
twyla.logging.egg-info/SOURCES.txt
twyla.logging.egg-info/dependency_links.txt
twyla.logging.egg-info/requires.txt
twyla.logging.egg-info/top_level.txt
twyla/logging/__init__.py
twyla/logging/formatters.py
twyla/logging/handlers.py