Metadata-Version: 1.0
Name: twyla.logging
Version: 0.0.3
Summary: Twyla Logging Utilities
Home-page: https://bitbucket.org/twyla/twyla.raml
Author: Twyla Devs
Author-email: dev@twylahelps.com
License: UNKNOWN
Platform: UNKNOWN
